inquestlabs.py
inquestlabs-1.2.4.dist-info/METADATA
inquestlabs-1.2.4.dist-info/WHEEL
inquestlabs-1.2.4.dist-info/entry_points.txt
inquestlabs-1.2.4.dist-info/licenses/LICENSE
inquestlabs-1.2.4.dist-info/RECORD
