Metadata-Version: 2.1
Name: inquestlabs
Version: 1.2.4
Summary: A Pythonic interface and CLI tool for the InQuest Labs API
Project-URL: Homepage, https://labs.inquest.net/
Project-URL: Repository, https://github.com/InQuest/python-inquestlabs
Project-URL: Bug Tracker, https://github.com/InQuest/python-inquestlabs/issues
Author-email: InQuest <labs@inquest.net>
License:                     GNU GENERAL PUBLIC LICENSE
License-File: LICENSE
Classifier: License :: OSI Approved :: GNU General Public License v2 (GPLv2)
Classifier: Operating System :: OS Independent
Classifier: Programming Language :: Python :: 3
Requires-Python: >=3.6
Requires-Dist: attrs
Requires-Dist: certifi
Requires-Dist: charset-normalizer
Requires-Dist: docopt
Requires-Dist: idna
Requires-Dist: iniconfig
Requires-Dist: packaging
Requires-Dist: pluggy
Requires-Dist: py
Requires-Dist: pyparsing
Requires-Dist: requests
Requires-Dist: six
Requires-Dist: tomli
Requires-Dist: urllib3
